example_package/__init__.py
example_package/jiug_hello.py
jiug_hello-0.3.1.dist-info/METADATA
jiug_hello-0.3.1.dist-info/WHEEL
jiug_hello-0.3.1.dist-info/entry_points.txt
jiug_hello-0.3.1.dist-info/RECORD
