Metadata-Version: 2.1
Name: jiug_hello
Version: 0.3.1
Summary: The Python program I'm distributing for the first time
Author-Email: jiughan <wldnd4081@gmail.com>
License: MIT
Project-URL: Homepage, https://github.com/Sam1000won/jiug
Project-URL: Bug tracker, https://github.com/Sam1000won/jiug/issues
Requires-Python: >=3.8
